{
  "diaObject": {
    "diaObjectId": 1007,
    "ra": 0.0,
    "decl": 0.0,
    "radecTai": 0.0,
    "uPSFluxMean": 0.0,
    "gPSFluxMean": 0.0,
    "rPSFluxMean": 0.0,
    "iPSFluxMean": 0.0,
    "zPSFluxMean": 0.0,
    "yPSFluxMean": 0.0
  },
  "diaSourcesList": [
    {
      "diaSourceId": 4801,
      "midPointTai": -8.954903601375893,
      "filterName": "i",
      "psFlux": 13022.393917112558,
      "psFluxErr": 1000
    },
    {
      "diaSourceId": 2284,
      "midPointTai": -8.50214129048984,
      "filterName": "y",
      "psFlux": 8061.554117528616,
      "psFluxErr": 1000
    },
    {
      "diaSourceId": 3931,
      "midPointTai": -8.32192502759694,
      "filterName": "z",
      "psFlux": 11099.05363106139,
      "psFluxErr": 1000
    },
    {
      "diaSourceId": 3455,
      "midPointTai": -7.968488931714486,
      "filterName": "y",
      "psFlux": 9196.413820395015,
      "psFluxErr": 1000
    },
    {
      "diaSourceId": 3289,
      "midPointTai": -6.820585686396786,
      "filterName": "i",
      "psFlux": 16112.48007280601,
      "psFluxErr": 1000
    },
    {
      "diaSourceId": 3617,
      "midPointTai": -6.293035694370783,
      "filterName": "u",
      "psFlux": 12175.30818939958,
      "psFluxErr": 1000
    },
    {
      "diaSourceId": 2663,
      "midPointTai": -5.882063887440545,
      "filterName": "r",
      "psFlux": 24208.667026777315,
      "psFluxErr": 1000
    },
    {
      "diaSourceId": 1671,
      "midPointTai": -5.637014618648276,
      "filterName": "i",
      "psFlux": 21489.259504976802,
      "psFluxErr": 1000
    },
    {
      "diaSourceId": 1990,
      "midPointTai": -4.920933018523144,
      "filterName": "y",
      "psFlux": 12377.738319835198,
      "psFluxErr": 1000
    },
    {
      "diaSourceId": 2874,
      "midPointTai": -4.562949161670968,
      "filterName": "u",
      "psFlux": 17524.59276028438,
      "psFluxErr": 1000
    },
    {
      "diaSourceId": 3482,
      "midPointTai": -4.313194257438305,
      "filterName": "i",
      "psFlux": 26302.642144904978,
      "psFluxErr": 1000
    },
    {
      "diaSourceId": 2909,
      "midPointTai": -4.20580285208192,
      "filterName": "y",
      "psFlux": 14746.85528266865,
      "psFluxErr": 1000
    },
    {
      "diaSourceId": 4954,
      "midPointTai": -3.8724349116390826,
      "filterName": "z",
      "psFlux": 21235.469720982634,
      "psFluxErr": 1000
    },
    {
      "diaSourceId": 4996,
      "midPointTai": -3.330072390075326,
      "filterName": "g",
      "psFlux": 30053.427394304654,
      "psFluxErr": 1000
    },
    {
      "diaSourceId": 4050,
      "midPointTai": -2.4752133304811785,
      "filterName": "i",
      "psFlux": 29800.187490753236,
      "psFluxErr": 1000
    },
    {
      "diaSourceId": 4474,
      "midPointTai": -0.35324286154287776,
      "filterName": "u",
      "psFlux": 26237.17068740739,
      "psFluxErr": 1000
    },
    {
      "diaSourceId": 2351,
      "midPointTai": -0.2492807947072535,
      "filterName": "u",
      "psFlux": 25408.231538368695,
      "psFluxErr": 1000
    },
    {
      "diaSourceId": 2202,
      "midPointTai": -0.18169466553169755,
      "filterName": "i",
      "psFlux": 38139.611864507555,
      "psFluxErr": 1000
    },
    {
      "diaSourceId": 3925,
      "midPointTai": 0.5549602881590197,
      "filterName": "i",
      "psFlux": 38434.2372688777,
      "psFluxErr": 1000
    },
    {
      "diaSourceId": 1567,
      "midPointTai": 0.7300472200967292,
      "filterName": "z",
      "psFlux": 30767.373194425552,
      "psFluxErr": 1000
    },
    {
      "diaSourceId": 2711,
      "midPointTai": 3.2885205169925626,
      "filterName": "i",
      "psFlux": 39241.66735207239,
      "psFluxErr": 1000
    },
    {
      "diaSourceId": 3453,
      "midPointTai": 4.1093205052473145,
      "filterName": "r",
      "psFlux": 43851.15133159321,
      "psFluxErr": 1000
    },
    {
      "diaSourceId": 1394,
      "midPointTai": 5.757692681073092,
      "filterName": "u",
      "psFlux": 26033.65276619765,
      "psFluxErr": 1000
    },
    {
      "diaSourceId": 4634,
      "midPointTai": 7.0829247891471,
      "filterName": "z",
      "psFlux": 25720.103475269854,
      "psFluxErr": 1000
    },
    {
      "diaSourceId": 2133,
      "midPointTai": 7.135805268987433,
      "filterName": "i",
      "psFlux": 32466.501947513632,
      "psFluxErr": 1000
    },
    {
      "diaSourceId": 3982,
      "midPointTai": 7.969589363177949,
      "filterName": "r",
      "psFlux": 33919.54343026981,
      "psFluxErr": 1000
    }
  ],
  "diaForcedSourcesList": [
    {
      "diaSourceId": 1378,
      "midPointTai": -11.724543962038702,
      "filterName": "y",
      "psFlux": 3974.4555372234427,
      "psFluxErr": 1000
    }
  ],
  "diaNondetectionLimitsList": [
    {
      "midPointTai": -19.79359711868848,
      "filterName": "u",
      "diaNoise": 2296.0036861797626
    },
    {
      "midPointTai": -18.67911130846126,
      "filterName": "u",
      "diaNoise": 2909.904571106973
    },
    {
      "midPointTai": -18.026162324980103,
      "filterName": "r",
      "diaNoise": 2648.760728081435
    },
    {
      "midPointTai": -18.006044119058654,
      "filterName": "y",
      "diaNoise": 1177.6550316827418
    },
    {
      "midPointTai": -17.73709460703188,
      "filterName": "z",
      "diaNoise": 1874.4045555368525
    },
    {
      "midPointTai": -17.2946910520376,
      "filterName": "y",
      "diaNoise": 322.2684024696357
    },
    {
      "midPointTai": -16.59606878625113,
      "filterName": "i",
      "diaNoise": 2123.558249646739
    },
    {
      "midPointTai": -16.40591369222583,
      "filterName": "r",
      "diaNoise": 3705.57054329188
    },
    {
      "midPointTai": -15.630592288893133,
      "filterName": "y",
      "diaNoise": 1481.4963017379987
    },
    {
      "midPointTai": -14.747459833513197,
      "filterName": "u",
      "diaNoise": 818.8866072670542
    },
    {
      "midPointTai": -14.160409099923342,
      "filterName": "y",
      "diaNoise": 3614.2210148386584
    },
    {
      "midPointTai": -13.815833236377914,
      "filterName": "z",
      "diaNoise": 2819.996512180466
    },
    {
      "midPointTai": -13.783046233423462,
      "filterName": "g",
      "diaNoise": 4196.961118798303
    }
  ]
}